xlcalc/__init__.py
xlcalc/compiler.py
xlcalc/dependency.py
xlcalc/evaluator.py
xlcalc/incremental_calculator.py
xlcalc/loader.py
xlcalc/logging_config.py
xlcalc/model.py
xlcalc/parser.py
xlcalc/references.py
xlcalc/utils.py
xlcalc/xltypes.py
xlcalc/funcs/__init__.py
xlcalc/funcs/date_funcs.py
xlcalc/funcs/date_utils.py
xlcalc/funcs/engineering_funcs.py
xlcalc/funcs/financial_funcs.py
xlcalc/funcs/func_xltypes.py
xlcalc/funcs/information_funcs.py
xlcalc/funcs/logical_funcs.py
xlcalc/funcs/lookup.py
xlcalc/funcs/math_funcs.py
xlcalc/funcs/statistics.py
xlcalc/funcs/text.py
xlcalc/funcs/xl.py
xlcalc/funcs/xlcriteria.py
xlcalc/funcs/xlerrors.py
xlcalcmodel-3.6.7.dist-info/licenses/LICENSE
xlcalcmodel-3.6.7.dist-info/METADATA
xlcalcmodel-3.6.7.dist-info/WHEEL
xlcalcmodel-3.6.7.dist-info/top_level.txt
xlcalcmodel-3.6.7.dist-info/RECORD
